torbi/_C.pt26cpu.abi3.so
torbi/_C.pt27cpu.abi3.so
torbi/_C.pt28cpu.abi3.so
torbi/__init__.py
torbi/__main__.py
torbi/chunk.py
torbi/core.py
torbi/viterbi.py
torbi/assets/partitions/daps.json
torbi/assets/partitions/vctk.json
torbi/assets/stats/transition.pt
torbi/config/__init__.py
torbi/config/defaults.py
torbi/config/static.py
torbi/data/__init__.py
torbi/data/collate.py
torbi/data/dataset.py
torbi/data/loader.py
torbi/data/download/__init__.py
torbi/data/download/__main__.py
torbi/data/download/core.py
torbi/data/preprocess/__init__.py
torbi/data/preprocess/__main__.py
torbi/data/preprocess/core.py
torbi/evaluate/__init__.py
torbi/evaluate/__main__.py
torbi/evaluate/core.py
torbi/evaluate/metrics.py
torbi/mps/__init__.py
torbi/mps/compiler.py
torbi/mps/viterbi.h
torbi/mps/viterbi.metal
torbi/mps/viterbi.mm
torbi/mps/viterbi.py
torbi/partition/__init__.py
torbi/partition/__main__.py
torbi/partition/core.py
torbi/reference/__init__.py
torbi/reference/core.py
torbi-1.3.3.dist-info/LICENSE
torbi-1.3.3.dist-info/METADATA
torbi-1.3.3.dist-info/WHEEL
torbi-1.3.3.dist-info/top_level.txt
torbi-1.3.3.dist-info/RECORD
