Metadata-Version: 2.1
Name: torbi
Version: 1.3.3
Summary: Optimized Viterbi decoding and fast approximations
Author-email: Cameron Churchwell <cameronchurchwell2024@u.northwestern.edu>, Max Morrison <maxrmorrison@gmail.com>
License: MIT License
Project-URL: Homepage, https://github.com/maxrmorrison/torbi
Project-URL: Issues, https://github.com/maxrmorrison/torbi/issues
Keywords: decode,sequence,torch,Viterbi
Classifier: License :: OSI Approved :: MIT License
Requires-Python: >=3.9
License-File: LICENSE
Requires-Dist: numpy
Requires-Dist: torch
Requires-Dist: torchutil
Requires-Dist: yapecs
Requires-Dist: tqdm
Requires-Dist: torchaudio
Requires-Dist: ninja; platform_system == "Darwin" and platform_machine == "arm64"
Provides-Extra: evaluate
Requires-Dist: librosa; extra == "evaluate"
Requires-Dist: torchaudio; extra == "evaluate"
Requires-Dist: pytest; extra == "evaluate"
Requires-Dist: penn; extra == "evaluate"
